proxy_checker_requests/__init__.py
proxy_checker_requests/proxy_checker.py
proxy_checker_requests-0.6.1.dist-info/LICENSE.md
proxy_checker_requests-0.6.1.dist-info/METADATA
proxy_checker_requests-0.6.1.dist-info/WHEEL
proxy_checker_requests-0.6.1.dist-info/top_level.txt
proxy_checker_requests-0.6.1.dist-info/RECORD
