Metadata-Version: 2.1
Name: proxy-checker-requests
Version: 0.6.1
Summary: Proxy checker in Python
Author: ricerati
Project-URL: Source Code, https://github.com/DedInc/proxy-checker-python
Keywords: proxy checker
Classifier: License :: OSI Approved :: MIT License
License-File: LICENSE.md
Requires-Dist: requests
